{
    "name": "zone2",
    "description": "Gideon adventures into the forest",
    "id": "",
    "objects": [
        {
            "name": "wolf",
            "transform": {
                "position": {
                    "x": 300,
                    "y": 150
                },
                "scale": {
                    "x": 2,
                    "y": 2
                }
            },
            "children": [],
            "components": [{
                    "name": "wolf_main",
                    "type": "animatedsprite",
                    "materialName": "wolf_walk",
                    "frameHeight": 80,
                    "frameWidth": 80,
                    "frameCount": 8,
                    "frameSequence": [0, 1, 2, 3, 4, 5, 6, 7]
                },
                {
                    "name": "wolfcollision",
                    "type": "collision",
                    "shape": {
                        "type": "rectangle",
                        "width": 80,
                        "height": 80
                    }
                }
            ],
            "behaviours": []
        }
    ]
}